<?xml version="1.0" encoding="UTF-8"?>
<ref id="ref27">
 <mixed-citation publication-type="other">
  <person-group person-group-type="author">
   <collab id="coll2">International Commission for Alpine Rescue</collab>
  </person-group> (
  <year>2016</year>). 
  <italic>20160115-AVA Deadly Avalanche Accidents Statistic 1983-2015.2016; Avalanche deaths by country and activity 1983-2015.</italic> Available at: 
  <ext-link ext-link-type="uri" xlink:href="http://www.alpine-rescue.org/xCMS5/WebObjects/nexus5.woa/wa/icar?menuid=1067&amp;rubricid=263&amp;articleid=12597" xmlns:xlink="http://www.w3.org/1999/xlink">http://www.alpine-rescue.org/xCMS5/WebObjects/nexus5.woa/wa/icar?menuid=1067&amp;rubricid=263&amp;articleid=12597</ext-link> (Accessed March 19, 2018).
 </mixed-citation>
</ref>
