<?xml version="1.0" encoding="UTF-8"?>
<fig id="nanomaterials-11-01840-f012" orientation="portrait" position="float">
 <label>Figure 12</label>
 <caption>
  <p>Comparison of (
   <bold>a</bold>) specific capacity increase and (
   <bold>b</bold>) areal capacity increase of cells with structured electrodes processed with different slurry pH values compared to cells with unstructured electrodes produced with the same slurry pH value.
  </p>
 </caption>
 <graphic xlink:href="nanomaterials-11-01840-g012" xmlns:xlink="http://www.w3.org/1999/xlink"/>
</fig>
