<?xml version="1.0" encoding="UTF-8"?>
<fig id="Fig6">
 <label>Fig. 6</label>
 <caption>
  <title>Relative change in global species richness from the community state at the onset of climate change (ordinate) over time (abscissa), averaged over replicates and given in 100-year steps (points).</title>
  <p>Black points correspond to species richness over the whole landscape; the blue points to richness in the top third of all patches (the polar region), green points to the middle third (temperate region), and yellow points to the last third (tropical region). Panel layout as in Fig. 
   <xref rid="Fig4" ref-type="fig">4</xref>; dotted horizontal lines highlight the point of no net change in global species richness.
  </p>
 </caption>
 <graphic xlink:href="41467_2021_24977_Fig6_HTML" id="d32e736" xmlns:xlink="http://www.w3.org/1999/xlink"/>
</fig>
