<?xml version="1.0" encoding="UTF-8"?>
<ref id="cssc202100364-bib-0025">
 <label>25</label>
 <mixed-citation publication-type="journal" id="cssc202100364-cit-0027">
  <string-name>
   <given-names>N.</given-names>
   <surname>Mahne</surname>
  </string-name>, 
  <string-name>
   <given-names>B.</given-names>
   <surname>Schafzahl</surname>
  </string-name>, 
  <string-name>
   <given-names>C.</given-names>
   <surname>Leypold</surname>
  </string-name>, 
  <string-name>
   <given-names>M.</given-names>
   <surname>Leypold</surname>
  </string-name>, 
  <string-name>
   <given-names>S.</given-names>
   <surname>Grumm</surname>
  </string-name>, 
  <string-name>
   <given-names>A.</given-names>
   <surname>Leitgeb</surname>
  </string-name>, 
  <string-name>
   <given-names>G. A.</given-names>
   <surname>Strohmeier</surname>
  </string-name>, 
  <string-name>
   <given-names>M.</given-names>
   <surname>Wilkening</surname>
  </string-name>, 
  <string-name>
   <given-names>O.</given-names>
   <surname>Fontaine</surname>
  </string-name>, 
  <string-name>
   <given-names>D.</given-names>
   <surname>Kramer</surname>
  </string-name>, 
  <string-name>
   <given-names>C.</given-names>
   <surname>Slugovc</surname>
  </string-name>, 
  <string-name>
   <given-names>S. M.</given-names>
   <surname>Borisov</surname>
  </string-name>, 
  <string-name>
   <given-names>S. A.</given-names>
   <surname>Freunberger</surname>
  </string-name>, 
  <source xml:lang="en">Nat. Energy</source>
  <year>2017</year>, 
  <volume>2</volume>, 
  <fpage>17036</fpage>.
 </mixed-citation>
</ref>
