<?xml version="1.0" encoding="UTF-8"?>
<ref id="cssc202100364-bib-0010">
 <label>10</label>
 <mixed-citation publication-type="journal" id="cssc202100364-cit-0011">
  <string-name>
   <given-names>D.</given-names>
   <surname>Schröder</surname>
  </string-name>, 
  <string-name>
   <given-names>C. L.</given-names>
   <surname>Bender</surname>
  </string-name>, 
  <string-name>
   <given-names>M.</given-names>
   <surname>Osenberg</surname>
  </string-name>, 
  <string-name>
   <given-names>A.</given-names>
   <surname>Hilger</surname>
  </string-name>, 
  <string-name>
   <given-names>I.</given-names>
   <surname>Manke</surname>
  </string-name>, 
  <string-name>
   <given-names>J.</given-names>
   <surname>Janek</surname>
  </string-name>, 
  <source xml:lang="en">Sci. Rep.</source>
  <year>2016</year>, 
  <volume>6</volume>, 
  <fpage>24288</fpage>.
  <pub-id pub-id-type="pmid">27068448</pub-id>
 </mixed-citation>
</ref>
