<?xml version="1.0" encoding="UTF-8"?>
<fig id="molecules-26-04531-f009" orientation="portrait" position="float">
 <label>Figure 9</label>
 <caption>
  <p>CV profiles of (
   <bold>a</bold>) uncalendered C/SiO
   <sub>2</sub>-0.085 M and (
   <bold>b</bold>) calendered C/SiO
   <sub>2</sub>-0.085 M, in the of 0.001–3 V voltage window, at a scan rate of 0.1 mV·s
   <sup>−1</sup>.
  </p>
 </caption>
 <graphic xlink:href="molecules-26-04531-g009" xmlns:xlink="http://www.w3.org/1999/xlink"/>
</fig>
