<?xml version="1.0" encoding="UTF-8"?>
<fig id="fig6" position="float">
 <label>Figure 6</label>
 <caption>
  <p>TBAGeCl
   <sub>3</sub> in 12CE: (a) Cyclic voltammetry of TBAGeCl
   <sub>3</sub>/12CE at graphene (
   <italic>A</italic> ≈ 0.3 cm
   <sup>2</sup>) and glassy carbon (
   <italic>A</italic> = 0.07 cm
   <sup>2</sup>) electrodes, 
   <italic>v</italic> = 50 mV s
   <sup>–1</sup>, Pt gauze auxiliary electrode, and Zn/Zn
   <sup>2+</sup> RE. Arrows indicate the sweep direction. For comparison, also voltammetric background cycles in neat 12 CE from 
   <xref rid="fig2" ref-type="fig">Figure 
    <xref rid="fig2" ref-type="fig">2</xref>
   </xref> are plotted. (b) SEM image of a graphene electrode with potentiostatically deposited Ge (−0.3 V for 260 s). Corresponding AFM data is shown in Supporting Information 
   <ext-link ext-link-type="uri" xlink:href="http://pubs.acs.org/doi/suppl/10.1021/acsami.0c11467/suppl_file/am0c11467_si_001.pdf" xmlns:xlink="http://www.w3.org/1999/xlink">Figure S8</ext-link>. White arrows indicate wrinkles in the graphene at which Ge islands nucleated. (c) Raman spectrum of a graphene electrode with potentiostatically deposited Ge. (d) SEM image of a graphene electrode with potentiostatically deposited Ge (−0.3 V for 7000 s).
  </p>
 </caption>
 <graphic xlink:href="am0c11467_0007" id="gr6" position="float" xmlns:xlink="http://www.w3.org/1999/xlink"/>
</fig>
