<?xml version="1.0" encoding="UTF-8"?>
<notes notes-type="data-availability">
 <title>Data Availability Statements</title>
 <p>Source data are cited in the article. 
  <xref ref-type="app" rid="app1-ijerph-18-07197">Supplementary Materials Tables S1 and S2</xref> are Excel spreadsheets with processed data from REDIAM (
  <xref ref-type="app" rid="app1-ijerph-18-07197">Supplementary Material Table S1</xref>) and the different cost calculations by pathology applied from the referenced literature and Andalusian Health Service data (
  <xref ref-type="app" rid="app1-ijerph-18-07197">Supplementary Material Table S2</xref>). 
  <uri xlink:href="https://drive.google.com/file/d/1LvqRyH_DV83waommEG5wdYI0ptbrQXWl/view?usp=sharing" xmlns:xlink="http://www.w3.org/1999/xlink">https://drive.google.com/file/d/1LvqRyH_DV83waommEG5wdYI0ptbrQXWl/view?usp=sharing</uri>; 
  <uri xlink:href="https://drive.google.com/file/d/1q_eTEw5HAvXm5aWU_s42eS9-Kce63ojS/view?usp=sharing" xmlns:xlink="http://www.w3.org/1999/xlink">https://drive.google.com/file/d/1q_eTEw5HAvXm5aWU_s42eS9-Kce63ojS/view?usp=sharing</uri> (accessed on 4 July 2021).
 </p>
</notes>
