<?xml version="1.0" encoding="UTF-8"?>
<fig id="molecules-25-05812-f004" orientation="portrait" position="float">
 <label>Figure 4</label>
 <caption>
  <p>Cyclic voltammetry of [hmim][NTf
   <sub>2</sub>] (—) and Eu(III) in [hmim][NTf
   <sub>2</sub>] (----) recorded at glassy carbon electrode. [Eu(III)] = 100 mM, scan rate = 100 mV/s, T = 373 K. Reproduced with permission of ref. [
   <xref rid="B35-molecules-25-05812" ref-type="bibr">35</xref>], copyright, 2015, Springer.
  </p>
 </caption>
 <graphic xlink:href="molecules-25-05812-g004" xmlns:xlink="http://www.w3.org/1999/xlink"/>
</fig>
