<?xml version="1.0" encoding="UTF-8"?>
<ref id="advs2021-bib-0020">
 <label>20</label>
 <mixed-citation publication-type="journal" id="advs2021-cit-0020">
  <string-name>
   <given-names>H.</given-names>
   <surname>Li</surname>
  </string-name>, 
  <string-name>
   <given-names>H.</given-names>
   <surname>Tang</surname>
  </string-name>, 
  <string-name>
   <given-names>C.</given-names>
   <surname>Ma</surname>
  </string-name>, 
  <string-name>
   <given-names>Y.</given-names>
   <surname>Bai</surname>
  </string-name>, 
  <string-name>
   <given-names>J.</given-names>
   <surname>Alvarado</surname>
  </string-name>, 
  <string-name>
   <given-names>B.</given-names>
   <surname>Radhakrishnan</surname>
  </string-name>, 
  <string-name>
   <given-names>S. P.</given-names>
   <surname>Ong</surname>
  </string-name>, 
  <string-name>
   <given-names>F.</given-names>
   <surname>Wu</surname>
  </string-name>, 
  <string-name>
   <given-names>Y. S.</given-names>
   <surname>Meng</surname>
  </string-name>, 
  <string-name>
   <given-names>C.</given-names>
   <surname>Wu</surname>
  </string-name>, 
  <source xml:lang="en">Chem. Mater.</source>
  <year>2018</year>, 
  <volume>30</volume>, 
  <fpage>2498</fpage>.
 </mixed-citation>
</ref>
